{
    "contributors": null,
    "coordinates": null,
    "created_at": "Mon Dec 16 10:42:21 +0000 2019",
    "display_text_range": [
        0,
        50
    ],
    "entities": {
        "urls": [
            {
                "indices": [
                    27,
                    50
                ],
                "url": "https://t.co/B5WWZhTrSu",
                "display_url": "toyokeizai.net/articles/-/319…",
                "expanded_url": "https://toyokeizai.net/articles/-/319079"
            }
        ],
        "hashtags": [],
        "url": {
            "urls": null
        },
        "user_mentions": [],
        "media": null
    },
    "extended_entities": {
        "urls": null,
        "hashtags": null,
        "url": {
            "urls": null
        },
        "user_mentions": null,
        "media": null
    },
    "extended_tweet": {
        "full_text": "",
        "display_text_range": null,
        "entities": {
            "urls": null,
            "hashtags": null,
            "url": {
                "urls": null
            },
            "user_mentions": null,
            "media": null
        },
        "extended_entities": {
            "urls": null,
            "hashtags": null,
            "url": {
                "urls": null
            },
            "user_mentions": null,
            "media": null
        }
    },
    "favorite_count": 0,
    "favorited": false,
    "filter_level": "",
    "full_text": "グレタさんで注目､｢飛び恥｣が鉄道に追い風 | 海外 https://t.co/B5WWZhTrSu",
    "has_extended_profile": false,
    "id": 1206524959960514561,
    "id_str": "1206524959960514561",
    "in_reply_to_screen_name": "",
    "in_reply_to_status_id": 0,
    "in_reply_to_status_id_str": "",
    "in_reply_to_user_id": 0,
    "in_reply_to_user_id_str": "",
    "is_translation_enabled": false,
    "lang": "ja",
    "place": {
        "attributes": null,
        "bounding_box": {
            "coordinates": null,
            "type": ""
        },
        "contained_within": null,
        "country": "",
        "country_code": "",
        "full_name": "",
        "geometry": {
            "coordinates": null,
            "type": ""
        },
        "id": "",
        "name": "",
        "place_type": "",
        "polylines": null,
        "url": ""
    },
    "quoted_status_id": 0,
    "quoted_status_id_str": "",
    "quoted_status": null,
    "possibly_sensitive": false,
    "possibly_sensitive_appealable": false,
    "retweet_count": 0,
    "retweeted": false,
    "retweeted_status": null,
    "source": "\u003ca href=\"http://www.facebook.com/twitter\" rel=\"nofollow\"\u003eFacebook\u003c/a\u003e",
    "scopes": null,
    "text": "グレタさんで注目､｢飛び恥｣が鉄\ufffd\ufffd",
    "user": {
        "contributors_enabled": false,
        "created_at": "Tue Jul 28 04:00:09 +0000 2009",
        "default_profile": true,
        "default_profile_image": false,
        "description": "デザイナーときどき大学講師ところにより文筆。講談社BOOK倶楽部＆コミックプラスにて編集者とのユニット筆名「野中幸宏」でブックレビュー連載中。https://t.co/cw63V3oWuZ",
        "email": "",
        "entities": {
            "urls": null,
            "hashtags": null,
            "url": {
                "urls": null
            },
            "user_mentions": null,
            "media": null
        },
        "favourites_count": 10129,
        "follow_request_sent": false,
        "followers_count": 1212,
        "following": false,
        "friends_count": 3145,
        "geo_enabled": true,
        "has_extended_profile": true,
        "id": 60804787,
        "id_str": "60804787",
        "is_translator": false,
        "is_translation_enabled": false,
        "lang": "",
        "listed_count": 55,
        "location": "東京 江東区",
        "name": "ナカノケン",
        "notifications": false,
        "profile_background_color": "C0DEED",
        "profile_background_image_url": "http://abs.twimg.com/images/themes/theme1/bg.png",
        "profile_background_image_url_https": "https://abs.twimg.com/images/themes/theme1/bg.png",
        "profile_background_tile": false,
        "profile_banner_url": "https://pbs.twimg.com/profile_banners/60804787/1460640115",
        "profile_image_url": "http://pbs.twimg.com/profile_images/780943033164455936/IJCUgVW5_normal.jpg",
        "profile_image_url_https": "https://pbs.twimg.com/profile_images/780943033164455936/IJCUgVW5_normal.jpg",
        "profile_link_color": "1DA1F2",
        "profile_sidebar_border_color": "C0DEED",
        "profile_sidebar_fill_color": "DDEEF6",
        "profile_text_color": "333333",
        "profile_use_background_image": true,
        "protected": false,
        "screen_name": "nakanoken",
        "show_all_inline_media": false,
        "status": null,
        "statuses_count": 187915,
        "time_zone": "",
        "url": "",
        "utc_offset": 0,
        "verified": false,
        "withheld_in_countries": null,
        "withheld_scope": ""
    },
    "withheld_copyright": false,
    "withheld_in_countries": null,
    "withheld_scope": ""
}