{
    "contributors": null,
    "coordinates": null,
    "created_at": "Tue Dec 17 05:29:45 +0000 2019",
    "display_text_range": [
        0,
        113
    ],
    "entities": {
        "urls": [
            {
                "indices": [
                    90,
                    113
                ],
                "url": "https://t.co/7jjMUk7MCJ",
                "display_url": "twitter.com/kabutociti/sta…",
                "expanded_url": "https://twitter.com/kabutociti/status/1206788009481256963"
            }
        ],
        "hashtags": [],
        "url": {
            "urls": null
        },
        "user_mentions": [
            {
                "name": "rea",
                "indices": [
                    3,
                    15
                ],
                "screen_name": "rea87736817",
                "id": 869126528742809600,
                "id_str": "869126528742809600"
            }
        ],
        "media": null
    },
    "extended_entities": {
        "urls": null,
        "hashtags": null,
        "url": {
            "urls": null
        },
        "user_mentions": null,
        "media": null
    },
    "extended_tweet": {
        "full_text": "",
        "display_text_range": null,
        "entities": {
            "urls": null,
            "hashtags": null,
            "url": {
                "urls": null
            },
            "user_mentions": null,
            "media": null
        },
        "extended_entities": {
            "urls": null,
            "hashtags": null,
            "url": {
                "urls": null
            },
            "user_mentions": null,
            "media": null
        }
    },
    "favorite_count": 0,
    "favorited": false,
    "filter_level": "",
    "full_text": "RT @rea87736817: グレタさんが朝の東西線に乗ったらみんなが電車に乗ってエコ！日本を見直した！とか思うのかな。東西線にファーストクラスはないの？とか言い出すのかな。 https://t.co/7jjMUk7MCJ",
    "has_extended_profile": false,
    "id": 1206808681657987072,
    "id_str": "1206808681657987072",
    "in_reply_to_screen_name": "",
    "in_reply_to_status_id": 0,
    "in_reply_to_status_id_str": "",
    "in_reply_to_user_id": 0,
    "in_reply_to_user_id_str": "",
    "is_translation_enabled": false,
    "lang": "ja",
    "place": {
        "attributes": null,
        "bounding_box": {
            "coordinates": null,
            "type": ""
        },
        "contained_within": null,
        "country": "",
        "country_code": "",
        "full_name": "",
        "geometry": {
            "coordinates": null,
            "type": ""
        },
        "id": "",
        "name": "",
        "place_type": "",
        "polylines": null,
        "url": ""
    },
    "quoted_status_id": 1206788009481256963,
    "quoted_status_id_str": "1206788009481256963",
    "quoted_status": null,
    "possibly_sensitive": false,
    "possibly_sensitive_appealable": false,
    "retweet_count": 6,
    "retweeted": false,
    "retweeted_status": {
        "contributors": null,
        "coordinates": null,
        "created_at": "Tue Dec 17 05:24:19 +0000 2019",
        "display_text_range": [
            0,
            72
        ],
        "entities": {
            "urls": [
                {
                    "indices": [
                        73,
                        96
                    ],
                    "url": "https://t.co/7jjMUk7MCJ",
                    "display_url": "twitter.com/kabutociti/sta…",
                    "expanded_url": "https://twitter.com/kabutociti/status/1206788009481256963"
                }
            ],
            "hashtags": [],
            "url": {
                "urls": null
            },
            "user_mentions": [],
            "media": null
        },
        "extended_entities": {
            "urls": null,
            "hashtags": null,
            "url": {
                "urls": null
            },
            "user_mentions": null,
            "media": null
        },
        "extended_tweet": {
            "full_text": "",
            "display_text_range": null,
            "entities": {
                "urls": null,
                "hashtags": null,
                "url": {
                    "urls": null
                },
                "user_mentions": null,
                "media": null
            },
            "extended_entities": {
                "urls": null,
                "hashtags": null,
                "url": {
                    "urls": null
                },
                "user_mentions": null,
                "media": null
            }
        },
        "favorite_count": 15,
        "favorited": false,
        "filter_level": "",
        "full_text": "グレタさんが朝の東西線に乗ったらみんなが電車に乗ってエコ！日本を見直した！とか思うのかな。東西線にファーストクラスはないの？とか言い出すのかな。 https://t.co/7jjMUk7MCJ",
        "has_extended_profile": false,
        "id": 1206807312419000322,
        "id_str": "1206807312419000322",
        "in_reply_to_screen_name": "",
        "in_reply_to_status_id": 0,
        "in_reply_to_status_id_str": "",
        "in_reply_to_user_id": 0,
        "in_reply_to_user_id_str": "",
        "is_translation_enabled": false,
        "lang": "ja",
        "place": {
            "attributes": null,
            "bounding_box": {
                "coordinates": null,
                "type": ""
            },
            "contained_within": null,
            "country": "",
            "country_code": "",
            "full_name": "",
            "geometry": {
                "coordinates": null,
                "type": ""
            },
            "id": "",
            "name": "",
            "place_type": "",
            "polylines": null,
            "url": ""
        },
        "quoted_status_id": 1206788009481256963,
        "quoted_status_id_str": "1206788009481256963",
        "quoted_status": {
            "contributors": null,
            "coordinates": null,
            "created_at": "Tue Dec 17 04:07:37 +0000 2019",
            "display_text_range": [
                0,
                73
            ],
            "entities": {
                "urls": [
                    {
                        "indices": [
                            36,
                            59
                        ],
                        "url": "https://t.co/ab7UyNt9Lq",
                        "display_url": "afpbb.com/articles/-/325…",
                        "expanded_url": "https://www.afpbb.com/articles/-/3259719"
                    }
                ],
                "hashtags": [],
                "url": {
                    "urls": null
                },
                "user_mentions": [
                    {
                        "name": "AFPBB News",
                        "indices": [
                            60,
                            69
                        ],
                        "screen_name": "afpbbcom",
                        "id": 90841111,
                        "id_str": "90841111"
                    }
                ],
                "media": null
            },
            "extended_entities": {
                "urls": null,
                "hashtags": null,
                "url": {
                    "urls": null
                },
                "user_mentions": null,
                "media": null
            },
            "extended_tweet": {
                "full_text": "",
                "display_text_range": null,
                "entities": {
                    "urls": null,
                    "hashtags": null,
                    "url": {
                        "urls": null
                    },
                    "user_mentions": null,
                    "media": null
                },
                "extended_entities": {
                    "urls": null,
                    "hashtags": null,
                    "url": {
                        "urls": null
                    },
                    "user_mentions": null,
                    "media": null
                }
            },
            "favorite_count": 4,
            "favorited": false,
            "filter_level": "",
            "full_text": "グレタさん「帰りの列車は超満員」  ドイツ鉄道とツイッターで小競り合い https://t.co/ab7UyNt9Lq @afpbbcomさんから",
            "has_extended_profile": false,
            "id": 1206788009481256963,
            "id_str": "1206788009481256963",
            "in_reply_to_screen_name": "",
            "in_reply_to_status_id": 0,
            "in_reply_to_status_id_str": "",
            "in_reply_to_user_id": 0,
            "in_reply_to_user_id_str": "",
            "is_translation_enabled": false,
            "lang": "ja",
            "place": {
                "attributes": null,
                "bounding_box": {
                    "coordinates": null,
                    "type": ""
                },
                "contained_within": null,
                "country": "",
                "country_code": "",
                "full_name": "",
                "geometry": {
                    "coordinates": null,
                    "type": ""
                },
                "id": "",
                "name": "",
                "place_type": "",
                "polylines": null,
                "url": ""
            },
            "quoted_status_id": 0,
            "quoted_status_id_str": "",
            "quoted_status": null,
            "possibly_sensitive": false,
            "possibly_sensitive_appealable": false,
            "retweet_count": 2,
            "retweeted": false,
            "retweeted_status": null,
            "source": "\u003ca href=\"http://twitter.com\" rel=\"nofollow\"\u003eTwitter Web Client\u003c/a\u003e",
            "scopes": null,
            "text": "グレタさん「帰りの列車は超満員」  ドイツ鉄道とツ\ufffd\ufffd",
            "user": {
                "contributors_enabled": false,
                "created_at": "Fri Apr 23 03:26:32 +0000 2010",
                "default_profile": true,
                "default_profile_image": false,
                "description": "株式・為替・経済情報を中心に配信。  Twitterの障害で入力できない場合はご容赦ください　英語の訳が下手というか無理なんで　間違ってたらごめんなさい。このツイッターで書かれている出来事、組織、人物はすべて架空のものであり、実在の存在とは一切係わり合いがございません。",
                "email": "",
                "entities": {
                    "urls": null,
                    "hashtags": null,
                    "url": {
                        "urls": null
                    },
                    "user_mentions": null,
                    "media": null
                },
                "favourites_count": 145468,
                "follow_request_sent": false,
                "followers_count": 46043,
                "following": false,
                "friends_count": 76,
                "geo_enabled": true,
                "has_extended_profile": false,
                "id": 136134010,
                "id_str": "136134010",
                "is_translator": false,
                "is_translation_enabled": false,
                "lang": "",
                "listed_count": 1405,
                "location": "満州国新京特別市",
                "name": "満州中央銀行",
                "notifications": false,
                "profile_background_color": "C0DEED",
                "profile_background_image_url": "http://abs.twimg.com/images/themes/theme1/bg.png",
                "profile_background_image_url_https": "https://abs.twimg.com/images/themes/theme1/bg.png",
                "profile_background_tile": false,
                "profile_banner_url": "",
                "profile_image_url": "http://pbs.twimg.com/profile_images/976626902/___normal.jpg",
                "profile_image_url_https": "https://pbs.twimg.com/profile_images/976626902/___normal.jpg",
                "profile_link_color": "1DA1F2",
                "profile_sidebar_border_color": "C0DEED",
                "profile_sidebar_fill_color": "DDEEF6",
                "profile_text_color": "333333",
                "profile_use_background_image": true,
                "protected": false,
                "screen_name": "kabutociti",
                "show_all_inline_media": false,
                "status": null,
                "statuses_count": 224269,
                "time_zone": "",
                "url": "",
                "utc_offset": 0,
                "verified": false,
                "withheld_in_countries": null,
                "withheld_scope": ""
            },
            "withheld_copyright": false,
            "withheld_in_countries": null,
            "withheld_scope": ""
        },
        "possibly_sensitive": false,
        "possibly_sensitive_appealable": false,
        "retweet_count": 6,
        "retweeted": false,
        "retweeted_status": null,
        "source": "\u003ca href=\"http://twitter.com/download/iphone\" rel=\"nofollow\"\u003eTwitter for iPhone\u003c/a\u003e",
        "scopes": null,
        "text": "グレタさんが朝の東西線に乗ったらみんなが電車に乗",
        "user": {
            "contributors_enabled": false,
            "created_at": "Mon May 29 09:41:26 +0000 2017",
            "default_profile": true,
            "default_profile_image": false,
            "description": "なんでも鑑定団 2018年 #クソ物件GO ワールドチャンピオン 内容は100%個人的見解",
            "email": "",
            "entities": {
                "urls": null,
                "hashtags": null,
                "url": {
                    "urls": null
                },
                "user_mentions": null,
                "media": null
            },
            "favourites_count": 8328,
            "follow_request_sent": false,
            "followers_count": 1507,
            "following": false,
            "friends_count": 491,
            "geo_enabled": true,
            "has_extended_profile": false,
            "id": 869126528742809600,
            "id_str": "869126528742809600",
            "is_translator": false,
            "is_translation_enabled": false,
            "lang": "",
            "listed_count": 41,
            "location": "",
            "name": "rea",
            "notifications": false,
            "profile_background_color": "F5F8FA",
            "profile_background_image_url": "",
            "profile_background_image_url_https": "",
            "profile_background_tile": false,
            "profile_banner_url": "https://pbs.twimg.com/profile_banners/869126528742809600/1566550235",
            "profile_image_url": "http://pbs.twimg.com/profile_images/1018980053751697409/B0V5LyzG_normal.jpg",
            "profile_image_url_https": "https://pbs.twimg.com/profile_images/1018980053751697409/B0V5LyzG_normal.jpg",
            "profile_link_color": "1DA1F2",
            "profile_sidebar_border_color": "C0DEED",
            "profile_sidebar_fill_color": "DDEEF6",
            "profile_text_color": "333333",
            "profile_use_background_image": true,
            "protected": false,
            "screen_name": "rea87736817",
            "show_all_inline_media": false,
            "status": null,
            "statuses_count": 6261,
            "time_zone": "",
            "url": "",
            "utc_offset": 0,
            "verified": false,
            "withheld_in_countries": null,
            "withheld_scope": ""
        },
        "withheld_copyright": false,
        "withheld_in_countries": null,
        "withheld_scope": ""
    },
    "source": "\u003ca href=\"https://mobile.twitter.com\" rel=\"nofollow\"\u003eTwitter Web App\u003c/a\u003e",
    "scopes": null,
    "text": "RT @rea87736817: グレタさんが朝の東西線に乗ったらみんなが電車に乗ってエコ！日本を",
    "user": {
        "contributors_enabled": false,
        "created_at": "Fri Apr 23 03:26:32 +0000 2010",
        "default_profile": true,
        "default_profile_image": false,
        "description": "株式・為替・経済情報を中心に配信。  Twitterの障害で入力できない場合はご容赦ください　英語の訳が下手というか無理なんで　間違ってたらごめんなさい。このツイッターで書かれている出来事、組織、人物はすべて架空のものであり、実在の存在とは一切係わり合いがございません。",
        "email": "",
        "entities": {
            "urls": null,
            "hashtags": null,
            "url": {
                "urls": null
            },
            "user_mentions": null,
            "media": null
        },
        "favourites_count": 145468,
        "follow_request_sent": false,
        "followers_count": 46043,
        "following": false,
        "friends_count": 76,
        "geo_enabled": true,
        "has_extended_profile": false,
        "id": 136134010,
        "id_str": "136134010",
        "is_translator": false,
        "is_translation_enabled": false,
        "lang": "",
        "listed_count": 1405,
        "location": "満州国新京特別市",
        "name": "満州中央銀行",
        "notifications": false,
        "profile_background_color": "C0DEED",
        "profile_background_image_url": "http://abs.twimg.com/images/themes/theme1/bg.png",
        "profile_background_image_url_https": "https://abs.twimg.com/images/themes/theme1/bg.png",
        "profile_background_tile": false,
        "profile_banner_url": "",
        "profile_image_url": "http://pbs.twimg.com/profile_images/976626902/___normal.jpg",
        "profile_image_url_https": "https://pbs.twimg.com/profile_images/976626902/___normal.jpg",
        "profile_link_color": "1DA1F2",
        "profile_sidebar_border_color": "C0DEED",
        "profile_sidebar_fill_color": "DDEEF6",
        "profile_text_color": "333333",
        "profile_use_background_image": true,
        "protected": false,
        "screen_name": "kabutociti",
        "show_all_inline_media": false,
        "status": null,
        "statuses_count": 224269,
        "time_zone": "",
        "url": "",
        "utc_offset": 0,
        "verified": false,
        "withheld_in_countries": null,
        "withheld_scope": ""
    },
    "withheld_copyright": false,
    "withheld_in_countries": null,
    "withheld_scope": ""
}