{
    "contributors": null,
    "coordinates": null,
    "created_at": "Mon Dec 16 09:52:43 +0000 2019",
    "display_text_range": [
        0,
        73
    ],
    "entities": {
        "urls": [
            {
                "indices": [
                    50,
                    73
                ],
                "url": "https://t.co/pgF7gv3K6X",
                "display_url": "afpbb.com/articles/-/325…",
                "expanded_url": "https://www.afpbb.com/articles/-/3259719?act=all"
            }
        ],
        "hashtags": [],
        "url": {
            "urls": null
        },
        "user_mentions": [],
        "media": null
    },
    "extended_entities": {
        "urls": null,
        "hashtags": null,
        "url": {
            "urls": null
        },
        "user_mentions": null,
        "media": null
    },
    "extended_tweet": {
        "full_text": "",
        "display_text_range": null,
        "entities": {
            "urls": null,
            "hashtags": null,
            "url": {
                "urls": null
            },
            "user_mentions": null,
            "media": null
        },
        "extended_entities": {
            "urls": null,
            "hashtags": null,
            "url": {
                "urls": null
            },
            "user_mentions": null,
            "media": null
        }
    },
    "favorite_count": 4,
    "favorited": false,
    "filter_level": "",
    "full_text": "なんかグレタさんに対して意地悪な感じするなぁと。ドイツの鉄道会社のイメージ云々あるでしょうけども。 https://t.co/pgF7gv3K6X",
    "has_extended_profile": false,
    "id": 1206512470338097152,
    "id_str": "1206512470338097152",
    "in_reply_to_screen_name": "",
    "in_reply_to_status_id": 0,
    "in_reply_to_status_id_str": "",
    "in_reply_to_user_id": 0,
    "in_reply_to_user_id_str": "",
    "is_translation_enabled": false,
    "lang": "ja",
    "place": {
        "attributes": null,
        "bounding_box": {
            "coordinates": null,
            "type": ""
        },
        "contained_within": null,
        "country": "",
        "country_code": "",
        "full_name": "",
        "geometry": {
            "coordinates": null,
            "type": ""
        },
        "id": "",
        "name": "",
        "place_type": "",
        "polylines": null,
        "url": ""
    },
    "quoted_status_id": 0,
    "quoted_status_id_str": "",
    "quoted_status": null,
    "possibly_sensitive": false,
    "possibly_sensitive_appealable": false,
    "retweet_count": 0,
    "retweeted": false,
    "retweeted_status": null,
    "source": "\u003ca href=\"http://twitter.com/download/android\" rel=\"nofollow\"\u003eTwitter for Android\u003c/a\u003e",
    "scopes": null,
    "text": "なんかグレタさんに対して意地悪な感じするなぁと。\ufffd",
    "user": {
        "contributors_enabled": false,
        "created_at": "Sun Feb 13 07:23:20 +0000 2011",
        "default_profile": false,
        "default_profile_image": false,
        "description": "小説家になろう、ネット詩ＭＹＤＥＡＲ、ｂ－ｒｅｖｉｅｗ、にて「夏生」というペンネームで詩を投稿しています。 宮尾節子さん、茨木のり子さん、吉野弘さん、辻征夫さん、などの作品に惹かれております。   個人的好みでは、沢田研二さんの生き様と歌に魅了されています。",
        "email": "",
        "entities": {
            "urls": null,
            "hashtags": null,
            "url": {
                "urls": null
            },
            "user_mentions": null,
            "media": null
        },
        "favourites_count": 103604,
        "follow_request_sent": false,
        "followers_count": 733,
        "following": false,
        "friends_count": 730,
        "geo_enabled": true,
        "has_extended_profile": false,
        "id": 251493918,
        "id_str": "251493918",
        "is_translator": false,
        "is_translation_enabled": false,
        "lang": "",
        "listed_count": 9,
        "location": "japan",
        "name": "夏生（なつお）",
        "notifications": false,
        "profile_background_color": "9AE4E8",
        "profile_background_image_url": "http://abs.twimg.com/images/themes/theme16/bg.gif",
        "profile_background_image_url_https": "https://abs.twimg.com/images/themes/theme16/bg.gif",
        "profile_background_tile": false,
        "profile_banner_url": "https://pbs.twimg.com/profile_banners/251493918/1516632386",
        "profile_image_url": "http://pbs.twimg.com/profile_images/715916296043388928/QOJ5oUQU_normal.jpg",
        "profile_image_url_https": "https://pbs.twimg.com/profile_images/715916296043388928/QOJ5oUQU_normal.jpg",
        "profile_link_color": "0084B4",
        "profile_sidebar_border_color": "BDDCAD",
        "profile_sidebar_fill_color": "DDFFCC",
        "profile_text_color": "333333",
        "profile_use_background_image": true,
        "protected": false,
        "screen_name": "tokisugi",
        "show_all_inline_media": false,
        "status": null,
        "statuses_count": 66195,
        "time_zone": "",
        "url": "",
        "utc_offset": 0,
        "verified": false,
        "withheld_in_countries": null,
        "withheld_scope": ""
    },
    "withheld_copyright": false,
    "withheld_in_countries": null,
    "withheld_scope": ""
}