{
    "contributors": null,
    "coordinates": null,
    "created_at": "Tue Dec 17 03:06:16 +0000 2019",
    "display_text_range": [
        0,
        124
    ],
    "entities": {
        "urls": [
            {
                "indices": [
                    125,
                    148
                ],
                "url": "https://t.co/LaE5PbuTp0",
                "display_url": "twitter.com/zakdesk/status…",
                "expanded_url": "https://twitter.com/zakdesk/status/1206769485241364483"
            }
        ],
        "hashtags": [],
        "url": {
            "urls": null
        },
        "user_mentions": [],
        "media": null
    },
    "extended_entities": {
        "urls": null,
        "hashtags": null,
        "url": {
            "urls": null
        },
        "user_mentions": null,
        "media": null
    },
    "extended_tweet": {
        "full_text": "",
        "display_text_range": null,
        "entities": {
            "urls": null,
            "hashtags": null,
            "url": {
                "urls": null
            },
            "user_mentions": null,
            "media": null
        },
        "extended_entities": {
            "urls": null,
            "hashtags": null,
            "url": {
                "urls": null
            },
            "user_mentions": null,
            "media": null
        }
    },
    "favorite_count": 4,
    "favorited": false,
    "filter_level": "",
    "full_text": "清貧のクレタちゃん、はじめから１等車のチケットなんてとらずに乗車すれば、よかったかもね・・・\n\n＞グレタさんは「バーゼルで列車が運行停止になってしまったので、私たちは２つの違う列車に乗り床の上に座った。ゲッティンゲンからは座席が確保できた」と釈明。 https://t.co/LaE5PbuTp0",
    "has_extended_profile": false,
    "id": 1206772571275853824,
    "id_str": "1206772571275853824",
    "in_reply_to_screen_name": "",
    "in_reply_to_status_id": 0,
    "in_reply_to_status_id_str": "",
    "in_reply_to_user_id": 0,
    "in_reply_to_user_id_str": "",
    "is_translation_enabled": false,
    "lang": "ja",
    "place": {
        "attributes": null,
        "bounding_box": {
            "coordinates": null,
            "type": ""
        },
        "contained_within": null,
        "country": "",
        "country_code": "",
        "full_name": "",
        "geometry": {
            "coordinates": null,
            "type": ""
        },
        "id": "",
        "name": "",
        "place_type": "",
        "polylines": null,
        "url": ""
    },
    "quoted_status_id": 1206769485241364483,
    "quoted_status_id_str": "1206769485241364483",
    "quoted_status": {
        "contributors": null,
        "coordinates": null,
        "created_at": "Tue Dec 17 02:54:00 +0000 2019",
        "display_text_range": [
            0,
            65
        ],
        "entities": {
            "urls": [
                {
                    "indices": [
                        42,
                        65
                    ],
                    "url": "https://t.co/zy3cF0sKka",
                    "display_url": "zakzak.co.jp/soc/news/19121…",
                    "expanded_url": "https://www.zakzak.co.jp/soc/news/191217/for1912170001-n1.html"
                }
            ],
            "hashtags": [],
            "url": {
                "urls": null
            },
            "user_mentions": [],
            "media": null
        },
        "extended_entities": {
            "urls": null,
            "hashtags": null,
            "url": {
                "urls": null
            },
            "user_mentions": null,
            "media": null
        },
        "extended_tweet": {
            "full_text": "",
            "display_text_range": null,
            "entities": {
                "urls": null,
                "hashtags": null,
                "url": {
                    "urls": null
                },
                "user_mentions": null,
                "media": null
            },
            "extended_entities": {
                "urls": null,
                "hashtags": null,
                "url": {
                    "urls": null
                },
                "user_mentions": null,
                "media": null
            }
        },
        "favorite_count": 11,
        "favorited": false,
        "filter_level": "",
        "full_text": "グレタさん「大混雑列車で床座り」ツイート　ドイツ鉄道「１等車だった」反論で“炎上” https://t.co/zy3cF0sKka",
        "has_extended_profile": false,
        "id": 1206769485241364483,
        "id_str": "1206769485241364483",
        "in_reply_to_screen_name": "",
        "in_reply_to_status_id": 0,
        "in_reply_to_status_id_str": "",
        "in_reply_to_user_id": 0,
        "in_reply_to_user_id_str": "",
        "is_translation_enabled": false,
        "lang": "ja",
        "place": {
            "attributes": null,
            "bounding_box": {
                "coordinates": null,
                "type": ""
            },
            "contained_within": null,
            "country": "",
            "country_code": "",
            "full_name": "",
            "geometry": {
                "coordinates": null,
                "type": ""
            },
            "id": "",
            "name": "",
            "place_type": "",
            "polylines": null,
            "url": ""
        },
        "quoted_status_id": 0,
        "quoted_status_id_str": "",
        "quoted_status": null,
        "possibly_sensitive": false,
        "possibly_sensitive_appealable": false,
        "retweet_count": 9,
        "retweeted": false,
        "retweeted_status": null,
        "source": "\u003ca href=\"https://buffer.com\" rel=\"nofollow\"\u003eBuffer\u003c/a\u003e",
        "scopes": null,
        "text": "グレタさん「大混雑列車で床座り」ツイート　\ufffd\ufffd",
        "user": {
            "contributors_enabled": false,
            "created_at": "Tue Aug 25 08:23:27 +0000 2009",
            "default_profile": false,
            "default_profile_image": false,
            "description": "エンタメから政治まで話題のニュースをお届けする夕刊フジ公式サイト「zakzak」編集部の公式ツイッターです。\n #夕刊フジ #夕フジ #zakzak",
            "email": "",
            "entities": {
                "urls": null,
                "hashtags": null,
                "url": {
                    "urls": [
                        {
                            "indices": [
                                0,
                                23
                            ],
                            "url": "https://t.co/U4m0keGDJU",
                            "display_url": "zakzak.co.jp",
                            "expanded_url": "https://www.zakzak.co.jp/"
                        }
                    ]
                },
                "user_mentions": null,
                "media": null
            },
            "favourites_count": 776,
            "follow_request_sent": false,
            "followers_count": 54553,
            "following": false,
            "friends_count": 1275,
            "geo_enabled": true,
            "has_extended_profile": false,
            "id": 68643433,
            "id_str": "68643433",
            "is_translator": false,
            "is_translation_enabled": false,
            "lang": "",
            "listed_count": 3782,
            "location": "東京都千代田区",
            "name": "zakzak",
            "notifications": false,
            "profile_background_color": "FFFFFF",
            "profile_background_image_url": "http://abs.twimg.com/images/themes/theme1/bg.png",
            "profile_background_image_url_https": "https://abs.twimg.com/images/themes/theme1/bg.png",
            "profile_background_tile": false,
            "profile_banner_url": "https://pbs.twimg.com/profile_banners/68643433/1476774711",
            "profile_image_url": "http://pbs.twimg.com/profile_images/382198781/zak_logo_normal.gif",
            "profile_image_url_https": "https://pbs.twimg.com/profile_images/382198781/zak_logo_normal.gif",
            "profile_link_color": "FF691F",
            "profile_sidebar_border_color": "D3D2CF",
            "profile_sidebar_fill_color": "E3E2DE",
            "profile_text_color": "634047",
            "profile_use_background_image": true,
            "protected": false,
            "screen_name": "zakdesk",
            "show_all_inline_media": false,
            "status": null,
            "statuses_count": 125024,
            "time_zone": "",
            "url": "https://t.co/U4m0keGDJU",
            "utc_offset": 0,
            "verified": true,
            "withheld_in_countries": null,
            "withheld_scope": ""
        },
        "withheld_copyright": false,
        "withheld_in_countries": null,
        "withheld_scope": ""
    },
    "possibly_sensitive": false,
    "possibly_sensitive_appealable": false,
    "retweet_count": 3,
    "retweeted": false,
    "retweeted_status": null,
    "source": "\u003ca href=\"http://twitter.com\" rel=\"nofollow\"\u003eTwitter Web Client\u003c/a\u003e",
    "scopes": null,
    "text": "清貧のクレタちゃん、はじめから１等車のチケットなんてとらずに乗車すれば、よかったか\ufffd",
    "user": {
        "contributors_enabled": false,
        "created_at": "Fri Jul 24 03:06:48 +0000 2009",
        "default_profile": false,
        "default_profile_image": false,
        "description": "JAPAN. KOBE. First-class-Architecte. Diving. Motorbike. Music. Photo. …幸も不幸も心の中に・風景- https://t.co/WzIgD46u7k  素敵なもの - https://t.co/9kGYnNs1nZ",
        "email": "",
        "entities": {
            "urls": null,
            "hashtags": null,
            "url": {
                "urls": [
                    {
                        "indices": [
                            0,
                            23
                        ],
                        "url": "https://t.co/fWMmqHDcJ4",
                        "display_url": "age.jp/~yume/aibbs/ai…",
                        "expanded_url": "http://www.age.jp/~yume/aibbs/aibbs3.cgi"
                    }
                ]
            },
            "user_mentions": null,
            "media": null
        },
        "favourites_count": 10886,
        "follow_request_sent": false,
        "followers_count": 1162,
        "following": false,
        "friends_count": 684,
        "geo_enabled": false,
        "has_extended_profile": false,
        "id": 59673254,
        "id_str": "59673254",
        "is_translator": false,
        "is_translation_enabled": false,
        "lang": "",
        "listed_count": 93,
        "location": "日本",
        "name": "宮崎和則",
        "notifications": false,
        "profile_background_color": "D4D2C9",
        "profile_background_image_url": "http://abs.twimg.com/images/themes/theme1/bg.png",
        "profile_background_image_url_https": "https://abs.twimg.com/images/themes/theme1/bg.png",
        "profile_background_tile": false,
        "profile_banner_url": "https://pbs.twimg.com/profile_banners/59673254/1570507493",
        "profile_image_url": "http://pbs.twimg.com/profile_images/1184061125844819969/zeDBQqme_normal.png",
        "profile_image_url_https": "https://pbs.twimg.com/profile_images/1184061125844819969/zeDBQqme_normal.png",
        "profile_link_color": "A6A59F",
        "profile_sidebar_border_color": "CCCCCC",
        "profile_sidebar_fill_color": "CFCEC3",
        "profile_text_color": "333333",
        "profile_use_background_image": false,
        "protected": false,
        "screen_name": "nori_miya",
        "show_all_inline_media": false,
        "status": null,
        "statuses_count": 105824,
        "time_zone": "",
        "url": "https://t.co/fWMmqHDcJ4",
        "utc_offset": 0,
        "verified": false,
        "withheld_in_countries": null,
        "withheld_scope": ""
    },
    "withheld_copyright": false,
    "withheld_in_countries": null,
    "withheld_scope": ""
}