{
    "contributors": null,
    "coordinates": null,
    "created_at": "Mon Dec 16 13:44:18 +0000 2019",
    "display_text_range": [
        0,
        127
    ],
    "entities": {
        "urls": [
            {
                "indices": [
                    65,
                    88
                ],
                "url": "https://t.co/mQ1U8eqVBZ",
                "display_url": "CNN.co.jp",
                "expanded_url": "http://CNN.co.jp"
            },
            {
                "indices": [
                    104,
                    127
                ],
                "url": "https://t.co/epo8gToUgK",
                "display_url": "htn.to/Yb9cGLZLzo",
                "expanded_url": "https://htn.to/Yb9cGLZLzo"
            }
        ],
        "hashtags": [],
        "url": {
            "urls": null
        },
        "user_mentions": [],
        "media": null
    },
    "extended_entities": {
        "urls": null,
        "hashtags": null,
        "url": {
            "urls": null
        },
        "user_mentions": null,
        "media": null
    },
    "extended_tweet": {
        "full_text": "",
        "display_text_range": null,
        "entities": {
            "urls": null,
            "hashtags": null,
            "url": {
                "urls": null
            },
            "user_mentions": null,
            "media": null
        },
        "extended_entities": {
            "urls": null,
            "hashtags": null,
            "url": {
                "urls": null
            },
            "user_mentions": null,
            "media": null
        }
    },
    "favorite_count": 0,
    "favorited": false,
    "filter_level": "",
    "full_text": "言ってる事が日本の右寄り左寄りオヤジ達と変わらん……。 / “ドイツ鉄道、グレタさんにツイッターで応酬　「混雑し過ぎ」と形容され（https://t.co/mQ1U8eqVBZ） - Yahoo!ニュース” https://t.co/epo8gToUgK",
    "has_extended_profile": false,
    "id": 1206570749831471104,
    "id_str": "1206570749831471104",
    "in_reply_to_screen_name": "",
    "in_reply_to_status_id": 0,
    "in_reply_to_status_id_str": "",
    "in_reply_to_user_id": 0,
    "in_reply_to_user_id_str": "",
    "is_translation_enabled": false,
    "lang": "ja",
    "place": {
        "attributes": null,
        "bounding_box": {
            "coordinates": null,
            "type": ""
        },
        "contained_within": null,
        "country": "",
        "country_code": "",
        "full_name": "",
        "geometry": {
            "coordinates": null,
            "type": ""
        },
        "id": "",
        "name": "",
        "place_type": "",
        "polylines": null,
        "url": ""
    },
    "quoted_status_id": 0,
    "quoted_status_id_str": "",
    "quoted_status": null,
    "possibly_sensitive": false,
    "possibly_sensitive_appealable": false,
    "retweet_count": 0,
    "retweeted": false,
    "retweeted_status": null,
    "source": "\u003ca href=\"http://b.hatena.ne.jp/\" rel=\"nofollow\"\u003eはてなブックマーク\u003c/a\u003e",
    "scopes": null,
    "text": "言ってる事が日本の右寄り左寄りオヤジ達と変わらん……。 / “ドイツ鉄道、グレタさんにツ\ufffd",
    "user": {
        "contributors_enabled": false,
        "created_at": "Thu Oct 15 17:06:53 +0000 2009",
        "default_profile": false,
        "default_profile_image": false,
        "description": "神奈川県在住。きっと何者にもなれない、ある意味無害な第二世代オタク。弱小はてな村民。猫とペンギンに埋もれたい勢。FGO、アイギス、花騎士、デレステ等プレイ中。つぶやき内容は雑多。リンクにはアフィリエイトが含まれる場合があります。",
        "email": "",
        "entities": {
            "urls": null,
            "hashtags": null,
            "url": {
                "urls": [
                    {
                        "indices": [
                            0,
                            23
                        ],
                        "url": "https://t.co/FYet3WRjiH",
                        "display_url": "sumida.hatenadiary.jp",
                        "expanded_url": "http://sumida.hatenadiary.jp/"
                    }
                ]
            },
            "user_mentions": null,
            "media": null
        },
        "favourites_count": 16633,
        "follow_request_sent": false,
        "followers_count": 302,
        "following": false,
        "friends_count": 1150,
        "geo_enabled": false,
        "has_extended_profile": true,
        "id": 82662512,
        "id_str": "82662512",
        "is_translator": false,
        "is_translation_enabled": false,
        "lang": "",
        "listed_count": 17,
        "location": "日本-関東",
        "name": "スミダ@たこわさ",
        "notifications": false,
        "profile_background_color": "C0DEED",
        "profile_background_image_url": "http://abs.twimg.com/images/themes/theme1/bg.png",
        "profile_background_image_url_https": "https://abs.twimg.com/images/themes/theme1/bg.png",
        "profile_background_tile": true,
        "profile_banner_url": "https://pbs.twimg.com/profile_banners/82662512/1490006911",
        "profile_image_url": "http://pbs.twimg.com/profile_images/621315608827662336/YpygoPlB_normal.png",
        "profile_image_url_https": "https://pbs.twimg.com/profile_images/621315608827662336/YpygoPlB_normal.png",
        "profile_link_color": "3B94D9",
        "profile_sidebar_border_color": "C0DEED",
        "profile_sidebar_fill_color": "DDEEF6",
        "profile_text_color": "333333",
        "profile_use_background_image": true,
        "protected": false,
        "screen_name": "sumidanger",
        "show_all_inline_media": false,
        "status": null,
        "statuses_count": 53884,
        "time_zone": "",
        "url": "https://t.co/FYet3WRjiH",
        "utc_offset": 0,
        "verified": false,
        "withheld_in_countries": null,
        "withheld_scope": ""
    },
    "withheld_copyright": false,
    "withheld_in_countries": null,
    "withheld_scope": ""
}