{
    "contributors": null,
    "coordinates": null,
    "created_at": "Tue Dec 17 06:43:41 +0000 2019",
    "display_text_range": [
        0,
        67
    ],
    "entities": {
        "urls": [
            {
                "indices": [
                    68,
                    91
                ],
                "url": "https://t.co/QdBVRnScTU",
                "display_url": "twitter.com/shoetsusato/st…",
                "expanded_url": "https://twitter.com/shoetsusato/status/1206333853683441664"
            }
        ],
        "hashtags": [],
        "url": {
            "urls": null
        },
        "user_mentions": [],
        "media": null
    },
    "extended_entities": {
        "urls": null,
        "hashtags": null,
        "url": {
            "urls": null
        },
        "user_mentions": null,
        "media": null
    },
    "extended_tweet": {
        "full_text": "",
        "display_text_range": null,
        "entities": {
            "urls": null,
            "hashtags": null,
            "url": {
                "urls": null
            },
            "user_mentions": null,
            "media": null
        },
        "extended_entities": {
            "urls": null,
            "hashtags": null,
            "url": {
                "urls": null
            },
            "user_mentions": null,
            "media": null
        }
    },
    "favorite_count": 4,
    "favorited": false,
    "filter_level": "",
    "full_text": "グレタさん\n\nこりゃひでぇ。この発想は暴力革命の共産主義者の言っている内容と同じ。\n\n洗脳されちゃってるのね・・かわいそうに(T_T) https://t.co/QdBVRnScTU",
    "has_extended_profile": false,
    "id": 1206827288072863745,
    "id_str": "1206827288072863745",
    "in_reply_to_screen_name": "",
    "in_reply_to_status_id": 0,
    "in_reply_to_status_id_str": "",
    "in_reply_to_user_id": 0,
    "in_reply_to_user_id_str": "",
    "is_translation_enabled": false,
    "lang": "ja",
    "place": {
        "attributes": null,
        "bounding_box": {
            "coordinates": null,
            "type": ""
        },
        "contained_within": null,
        "country": "",
        "country_code": "",
        "full_name": "",
        "geometry": {
            "coordinates": null,
            "type": ""
        },
        "id": "",
        "name": "",
        "place_type": "",
        "polylines": null,
        "url": ""
    },
    "quoted_status_id": 1206333853683441664,
    "quoted_status_id_str": "1206333853683441664",
    "quoted_status": {
        "contributors": null,
        "coordinates": null,
        "created_at": "Sun Dec 15 22:02:57 +0000 2019",
        "display_text_range": [
            0,
            139
        ],
        "entities": {
            "urls": [
                {
                    "indices": [
                        116,
                        139
                    ],
                    "url": "https://t.co/7A3QjO0LeS",
                    "display_url": "moeruasia.net/archives/49657…",
                    "expanded_url": "https://www.moeruasia.net/archives/49657134.html"
                }
            ],
            "hashtags": [],
            "url": {
                "urls": null
            },
            "user_mentions": [],
            "media": null
        },
        "extended_entities": {
            "urls": null,
            "hashtags": null,
            "url": {
                "urls": null
            },
            "user_mentions": null,
            "media": null
        },
        "extended_tweet": {
            "full_text": "",
            "display_text_range": null,
            "entities": {
                "urls": null,
                "hashtags": null,
                "url": {
                    "urls": null
                },
                "user_mentions": null,
                "media": null
            },
            "extended_entities": {
                "urls": null,
                "hashtags": null,
                "url": {
                    "urls": null
                },
                "user_mentions": null,
                "media": null
            }
        },
        "favorite_count": 2962,
        "favorited": false,
        "filter_level": "",
        "full_text": "子の子は学校教育の中で人間関係の基本を学習してからでないと、ダメだな、大人のおもちゃにされている事に気ついていない。\n\nグレタさん、自分に従わない指導者は「against the wall」(壁際に立たせる=銃殺刑)　大炎上、謝罪 https://t.co/7A3QjO0LeS",
        "has_extended_profile": false,
        "id": 1206333853683441664,
        "id_str": "1206333853683441664",
        "in_reply_to_screen_name": "",
        "in_reply_to_status_id": 0,
        "in_reply_to_status_id_str": "",
        "in_reply_to_user_id": 0,
        "in_reply_to_user_id_str": "",
        "is_translation_enabled": false,
        "lang": "ja",
        "place": {
            "attributes": null,
            "bounding_box": {
                "coordinates": null,
                "type": ""
            },
            "contained_within": null,
            "country": "",
            "country_code": "",
            "full_name": "",
            "geometry": {
                "coordinates": null,
                "type": ""
            },
            "id": "",
            "name": "",
            "place_type": "",
            "polylines": null,
            "url": ""
        },
        "quoted_status_id": 0,
        "quoted_status_id_str": "",
        "quoted_status": null,
        "possibly_sensitive": false,
        "possibly_sensitive_appealable": false,
        "retweet_count": 1408,
        "retweeted": false,
        "retweeted_status": null,
        "source": "\u003ca href=\"http://twitter.com\" rel=\"nofollow\"\u003eTwitter Web Client\u003c/a\u003e",
        "scopes": null,
        "text": "子の子は学校教育の中で人間関係の基本を学習してからでないと、ダメだな、大人のおもちゃにされて\ufffd",
        "user": {
            "contributors_enabled": false,
            "created_at": "Sun Oct 26 03:04:05 +0000 2014",
            "default_profile": false,
            "default_profile_image": false,
            "description": "北の大地で田舎暮し。凛とした日本人の心とそれを育んだ日本の伝統・文化・自然を大切に守り、歴史に学び、自主憲法制定、反日偏向報道を繰返すマスメディアの撲滅を。画像は私が育てたヒマワリと地先山、アイコンは救出した迷子猫親子。誤字、脱字、無言フォローをご容赦ください。",
            "email": "",
            "entities": {
                "urls": null,
                "hashtags": null,
                "url": {
                    "urls": null
                },
                "user_mentions": null,
                "media": null
            },
            "favourites_count": 72601,
            "follow_request_sent": false,
            "followers_count": 49529,
            "following": false,
            "friends_count": 47094,
            "geo_enabled": true,
            "has_extended_profile": true,
            "id": 2877651816,
            "id_str": "2877651816",
            "is_translator": false,
            "is_translation_enabled": false,
            "lang": "",
            "listed_count": 195,
            "location": "北の大地",
            "name": "田舎暮しの唱悦",
            "notifications": false,
            "profile_background_color": "000000",
            "profile_background_image_url": "http://abs.twimg.com/images/themes/theme1/bg.png",
            "profile_background_image_url_https": "https://abs.twimg.com/images/themes/theme1/bg.png",
            "profile_background_tile": false,
            "profile_banner_url": "https://pbs.twimg.com/profile_banners/2877651816/1481522243",
            "profile_image_url": "http://pbs.twimg.com/profile_images/808426778091868160/Zz-uoPhb_normal.jpg",
            "profile_image_url_https": "https://pbs.twimg.com/profile_images/808426778091868160/Zz-uoPhb_normal.jpg",
            "profile_link_color": "0236F2",
            "profile_sidebar_border_color": "000000",
            "profile_sidebar_fill_color": "000000",
            "profile_text_color": "000000",
            "profile_use_background_image": false,
            "protected": false,
            "screen_name": "shoetsusato",
            "show_all_inline_media": false,
            "status": null,
            "statuses_count": 95616,
            "time_zone": "",
            "url": "",
            "utc_offset": 0,
            "verified": false,
            "withheld_in_countries": null,
            "withheld_scope": ""
        },
        "withheld_copyright": false,
        "withheld_in_countries": null,
        "withheld_scope": ""
    },
    "possibly_sensitive": false,
    "possibly_sensitive_appealable": false,
    "retweet_count": 1,
    "retweeted": false,
    "retweeted_status": null,
    "source": "\u003ca href=\"http://twitter.com\" rel=\"nofollow\"\u003eTwitter Web Client\u003c/a\u003e",
    "scopes": null,
    "text": "グレタさん\n\nこりゃひでぇ。この発想は暴力革命\ufffd\ufffd",
    "user": {
        "contributors_enabled": false,
        "created_at": "Thu Jul 22 14:23:06 +0000 2010",
        "default_profile": false,
        "default_profile_image": false,
        "description": "・旧アカウント名　KSM WORLD ・旧車・古いもの大好き・音楽大好き・投資家（株式・不動産）賃貸経営・軽貨物・元英語教師 ・正義と真実の歴史が好き。日本の左翼とは違う愛国リベラル。・YouTube、ツイキャスで雑談配信。　日本大好きな新潟県民。 https://t.co/mrioYa48sv…",
        "email": "",
        "entities": {
            "urls": null,
            "hashtags": null,
            "url": {
                "urls": [
                    {
                        "indices": [
                            0,
                            23
                        ],
                        "url": "https://t.co/4dXuVPlocp",
                        "display_url": "twitcasting.tv/brave_japanese",
                        "expanded_url": "https://twitcasting.tv/brave_japanese"
                    }
                ]
            },
            "user_mentions": null,
            "media": null
        },
        "favourites_count": 18967,
        "follow_request_sent": false,
        "followers_count": 8715,
        "following": false,
        "friends_count": 9589,
        "geo_enabled": false,
        "has_extended_profile": true,
        "id": 169508950,
        "id_str": "169508950",
        "is_translator": false,
        "is_translation_enabled": false,
        "lang": "",
        "listed_count": 90,
        "location": "新潟 新潟市 中央区",
        "name": "かわちゃん（にっぽん大好き！！）",
        "notifications": false,
        "profile_background_color": "000000",
        "profile_background_image_url": "http://abs.twimg.com/images/themes/theme4/bg.gif",
        "profile_background_image_url_https": "https://abs.twimg.com/images/themes/theme4/bg.gif",
        "profile_background_tile": false,
        "profile_banner_url": "https://pbs.twimg.com/profile_banners/169508950/1571036384",
        "profile_image_url": "http://pbs.twimg.com/profile_images/1205034012269371392/HPszhNbR_normal.png",
        "profile_image_url_https": "https://pbs.twimg.com/profile_images/1205034012269371392/HPszhNbR_normal.png",
        "profile_link_color": "1B95E0",
        "profile_sidebar_border_color": "000000",
        "profile_sidebar_fill_color": "000000",
        "profile_text_color": "000000",
        "profile_use_background_image": false,
        "protected": false,
        "screen_name": "Brave_Japanese",
        "show_all_inline_media": false,
        "status": null,
        "statuses_count": 63366,
        "time_zone": "",
        "url": "https://t.co/4dXuVPlocp",
        "utc_offset": 0,
        "verified": false,
        "withheld_in_countries": null,
        "withheld_scope": ""
    },
    "withheld_copyright": false,
    "withheld_in_countries": null,
    "withheld_scope": ""
}